kgeditor/__init__.py
kgeditor/kgeditor.py
kgeditor/one_shot_learner.py
kgeditor/run.py
kgeditor/trainer.py
kgeditor/src/__init__.py
kgeditor/src/data/__init__.py
kgeditor/src/data/data_module.py
kgeditor/src/data/processor.py
kgeditor/src/models/__init__.py
kgeditor/src/models/modeling_bert.py
kgeditor/src/models/models.py
kgeditor/src/models/one_shot_learner.py
kgeditor-1.0.0.dist-info/LICENSE.txt
kgeditor-1.0.0.dist-info/METADATA
kgeditor-1.0.0.dist-info/WHEEL
kgeditor-1.0.0.dist-info/top_level.txt
kgeditor-1.0.0.dist-info/RECORD
