Metadata-Version: 2.1
Name: kgeditor
Version: 1.0.0
Summary: A library that provides a tool to edit model easily.
Home-page: https://github.com/zjunlp/PromptKG/tree/main/deltaKG
Author: Bozhong Tian
Author-email: tbozhong@163.com
Keywords: knowledge graph embedding edit
Classifier: Programming Language :: Python :: 3
Classifier: License :: OSI Approved :: MIT License
Classifier: Operating System :: OS Independent
Requires-Python: >=3.6
License-File: LICENSE.txt
